[    
    {
        "name": "Forest snow",
        "url": "/themes-nav/wallpapers/animated/background3.gif",
        "type": "animated",
        "theme": "landscapes"
    },
    {
        "name": "beadroom",
        "url": "/themes-nav/wallpapers/static/background1.png",
        "type": "static",
        "theme": "landscapes"
    },
    {
        "name": "Skye",
        "url": "/themes-nav/wallpapers/static/background2.png",
        "type": "static",
        "theme": "landscapes"
    },
    {
        "name": "Forest night",
        "url": "/themes-nav/wallpapers/static/background3.png",
        "type": "static",
        "theme": "landscapes"
    },
    {
        "name": "Sunset beach",
        "url": "/themes-nav/wallpapers/static/background4.png",
        "type": "static",
        "theme": "landscapes"
    },
    {
        "name": "Test",
        "url": "/themes-nav/wallpapers/static/background3.png",
        "type": "static",
        "theme": "landscapes"
    },
    {
        "name": "Test",
        "url": "/themes-nav/wallpapers/static/background3.png",
        "type": "static",
        "theme": "landscapes"
    },
    {
        "name": "Test",
        "url": "/themes-nav/wallpapers/static/background3.png",
        "type": "static",
        "theme": "landscapes"
    },
    {
        "name": "Test",
        "url": "/themes-nav/wallpapers/static/background3.png",
        "type": "static",
        "theme": "landscapes"
    },
    {
        "name": "Test",
        "url": "/themes-nav/wallpapers/static/background3.png",
        "type": "static",
        "theme": "landscapes"
    }
]
